setup.py
bxt_description_generator/__init__.py
bxt_description_generator/bxt_description_generator.py
bxt_description_generator/models.py
bxt_description_generator.egg-info/PKG-INFO
bxt_description_generator.egg-info/SOURCES.txt
bxt_description_generator.egg-info/dependency_links.txt
bxt_description_generator.egg-info/entry_points.txt
bxt_description_generator.egg-info/not-zip-safe
bxt_description_generator.egg-info/requires.txt
bxt_description_generator.egg-info/top_level.txt