Metadata-Version: 1.0
Name: bxt-description-generator
Version: 0.3
Summary: BoxTorrents Description Generator
Home-page: http://github.com/xiongchiamiov/bxt-description-generator
Author: xiong_chiamiov
Author-email: xiong.chiamiov@gmail.com
License: WTFPL
Platform: UNKNOWN
Classifier: Development Status :: 4 - Beta
Classifier: Environment :: Console
Classifier: License :: Other/Proprietary License
Classifier: Operating System :: OS Independent
Classifier: Programming Language :: Python
Classifier: Topic :: Internet
